math_object/__init__.py
math_object/point2d.py
math_object/polygon2d.py
math_object/py.typed
schema/__init__.py
schema/exercise_definition.py
schema/py.typed
schema/solution.py
mk_core-0.1.dist-info/LICENSE
mk_core-0.1.dist-info/METADATA
mk_core-0.1.dist-info/WHEEL
mk_core-0.1.dist-info/top_level.txt
mk_core-0.1.dist-info/RECORD
